sk2torch/__init__.py
sk2torch/dummy.py
sk2torch/dummy_test.py
sk2torch/gradient_boosting.py
sk2torch/gradient_boosting_test.py
sk2torch/kernel.py
sk2torch/kernel_test.py
sk2torch/label_binarizer.py
sk2torch/label_binarizer_test.py
sk2torch/linear_model.py
sk2torch/linear_model_test.py
sk2torch/nn.py
sk2torch/nn_test.py
sk2torch/nystroem.py
sk2torch/nystroem_test.py
sk2torch/pca.py
sk2torch/pca_test.py
sk2torch/pipeline.py
sk2torch/pipeline_test.py
sk2torch/stacking.py
sk2torch/stacking_test.py
sk2torch/standard_scaler.py
sk2torch/standard_scaler_test.py
sk2torch/svc.py
sk2torch/svc_test.py
sk2torch/svr.py
sk2torch/svr_test.py
sk2torch/tree.py
sk2torch/tree_test.py
sk2torch/ttr.py
sk2torch/ttr_test.py
sk2torch/util.py
sk2torch/wrap.py
sk2torch-1.1.0.dist-info/METADATA
sk2torch-1.1.0.dist-info/WHEEL
sk2torch-1.1.0.dist-info/top_level.txt
sk2torch-1.1.0.dist-info/RECORD
